image_display.py
ImageDisplayQT-1.1.0.dist-info/LICENSE
ImageDisplayQT-1.1.0.dist-info/METADATA
ImageDisplayQT-1.1.0.dist-info/WHEEL
ImageDisplayQT-1.1.0.dist-info/top_level.txt
ImageDisplayQT-1.1.0.dist-info/RECORD
