Metadata-Version: 2.1
Name: ImageDisplayQT
Version: 1.1.0
Summary: A widget for real time image display in PyQT GUIs.
Author-email: Michael Hughes <m.r.hughes@kent.ac.uk>
License: MIT License
Project-URL: Homepage, https://github.com/MikeHughesKent/ImageDisplayQT/
Keywords: imaging,GUI,display,video,PyQT,QT,scientific
Classifier: License :: OSI Approved :: MIT License
Classifier: Programming Language :: Python
Classifier: Programming Language :: Python :: 3
Requires-Python: >=3.8
License-File: LICENSE
Requires-Dist: numpy >=1.18
Requires-Dist: Pillow >=9.3.0
Requires-Dist: matplotlib >=3.3.4
Requires-Dist: PyQT5 >=5.15.0
Provides-Extra: dev
